strong_passphrase/__init__.py
strong_passphrase/eng_words.py
strong_passphrase/flavour_text.py
strong_passphrase-0.0.1.dist-info/METADATA
strong_passphrase-0.0.1.dist-info/WHEEL
strong_passphrase-0.0.1.dist-info/entry_points.txt
strong_passphrase-0.0.1.dist-info/licenses/LICENSE
strong_passphrase-0.0.1.dist-info/RECORD
