Metadata-Version: 2.3
Name: strong-passphrase
Version: 0.0.1
Summary: Generate strong passphrases from the command line.
Project-URL: Homepage, https://github.com/danieljohnprojects/strong-passphrase
Project-URL: Issues, https://github.com/danieljohnprojects/strong-passphrase/issues
Author-email: Daniel John <daniel.john.projects@gmail.com>
License-File: LICENSE
Classifier: License :: OSI Approved :: MIT License
Classifier: Operating System :: OS Independent
Classifier: Programming Language :: Python :: 3
Requires-Python: >=3.9
